pyinstrument/__init__.py
pyinstrument/__main__.py
pyinstrument/frame.py
pyinstrument/middleware.py
pyinstrument/processors.py
pyinstrument/profiler.py
pyinstrument/session.py
pyinstrument/util.py
pyinstrument/renderers/__init__.py
pyinstrument/renderers/base.py
pyinstrument/renderers/console.py
pyinstrument/renderers/html.py
pyinstrument/renderers/jsonrenderer.py
pyinstrument/vendor/__init__.py
pyinstrument/vendor/decorator.py
pyinstrument/vendor/six.py
test/__init__.py
test/busywait.py
test/test_cmdline.py
test/test_overflow.py
test/test_processors.py
test/test_profiler.py
test/busywait_module/__init__.py
test/busywait_module/__main__.py
pyinstrument1-3.1.3.dist-info/LICENSE
pyinstrument1-3.1.3.dist-info/METADATA
pyinstrument1-3.1.3.dist-info/WHEEL
pyinstrument1-3.1.3.dist-info/entry_points.txt
pyinstrument1-3.1.3.dist-info/top_level.txt
pyinstrument1-3.1.3.dist-info/RECORD
