Metadata-Version: 2.1
Name: pyinstrument1
Version: 3.1.3
Summary: Call stack profiler for Python. Shows you why your code is slow!
Home-page: https://github.com/joerick/pyinstrument
Author: Joe Rickerby
Author-email: joerick@mac.com
License: UNKNOWN
Keywords: profiling,profile,profiler,cpu,time,sampling
Platform: UNKNOWN
Classifier: Environment :: Console
Classifier: Environment :: Web Environment
Classifier: Intended Audience :: Developers
Classifier: License :: OSI Approved :: BSD License
Classifier: Operating System :: MacOS
Classifier: Operating System :: Microsoft :: Windows
Classifier: Operating System :: POSIX
Classifier: Programming Language :: Python :: 2.7
Classifier: Programming Language :: Python :: 3.3
Classifier: Programming Language :: Python :: 3.4
Classifier: Programming Language :: Python :: 3.5
Classifier: Programming Language :: Python :: 3.6
Classifier: Programming Language :: Python :: 3.7
Classifier: Topic :: Software Development :: Debuggers
Classifier: Topic :: Software Development :: Testing
Requires-Dist: pyinstrument-cext (>=0.2.2)
